streaming_weights/__init__.py
streaming_weights/chunker.py
streaming_weights/config.py
streaming_weights/monitoring.py
streaming_weights/streaming_bert.py
streaming_weights/utils.py
streaming_weights/weight_server.py
streaming_weights/models/__init__.py
streaming_weights/models/base.py
streaming_weights/models/bert.py
streaming_weights/models/gpt.py
streaming_weights/models/llama.py
streaming_weights/models/t5.py
streaming_weights/storage/__init__.py
streaming_weights/storage/base.py
streaming_weights/storage/filesystem.py
streaming_weights/storage/s3.py
streaming_weights-0.1.1.dist-info/licenses/LICENSE
streaming_weights-0.1.1.dist-info/METADATA
streaming_weights-0.1.1.dist-info/WHEEL
streaming_weights-0.1.1.dist-info/top_level.txt
streaming_weights-0.1.1.dist-info/RECORD
