Metadata-Version: 2.4
Name: streaming-weights
Version: 0.1.1
Summary: Streaming weights engine for edge AI deployment
Home-page: https://github.com/Adarshreddyash/surfing-weights
Author: Adarsh Reddy
Author-email: Adarsh Reddy <adarshadelli@gmail.com>
License: MIT
Project-URL: Homepage, https://github.com/yourusername/surfing
Project-URL: Bug Tracker, https://github.com/yourusername/surfing/issues
Classifier: Programming Language :: Python :: 3
Classifier: License :: OSI Approved :: MIT License
Classifier: Operating System :: OS Independent
Classifier: Topic :: Scientific/Engineering :: Artificial Intelligence
Requires-Python: >=3.8
License-File: LICENSE
Requires-Dist: torch>=1.10.0
Requires-Dist: transformers>=4.20.0
Requires-Dist: websockets>=10.0
Requires-Dist: numpy>=1.20.0
Requires-Dist: tqdm>=4.62.0
Provides-Extra: s3
Requires-Dist: boto3>=1.20.0; extra == "s3"
Provides-Extra: dev
Requires-Dist: pytest>=6.0; extra == "dev"
Requires-Dist: black>=22.0; extra == "dev"
Requires-Dist: isort>=5.0; extra == "dev"
Requires-Dist: flake8>=4.0; extra == "dev"
Dynamic: author
Dynamic: home-page
Dynamic: license-file
Dynamic: requires-python
